Metadata-Version: 2.4
Name: llm-fragments-youtube
Version: 0.1.1
Summary: LLM plugin for loading YouTube subtitles as fragments
Author-email: "Agustin B." <redraw@sdf.org>
License: MIT
Project-URL: Homepage, https://github.com/redraw/llm-fragments-youtube
Project-URL: Issues, https://github.com/redraw/llm-fragments-youtube/issues
Classifier: Development Status :: 3 - Alpha
Classifier: Intended Audience :: Developers
Classifier: License :: OSI Approved :: MIT License
Classifier: Programming Language :: Python :: 3
Classifier: Programming Language :: Python :: 3.9
Classifier: Programming Language :: Python :: 3.10
Classifier: Programming Language :: Python :: 3.11
Requires-Python: >=3.9
License-File: LICENSE
Requires-Dist: llm
Requires-Dist: yt-dlp
Provides-Extra: test
Requires-Dist: pytest; extra == "test"
Requires-Dist: pytest-cov; extra == "test"
Dynamic: license-file
